{"rows":50,"cols":26,"cells":{"0":{"0":{"inBounds":true,"difficultTerrain":false,"tileNumber":"23A"},"1":{"inBounds":true,"difficultTerrain":false},"2":{"inBounds":true,"difficultTerrain":false},"3":{"inBounds":true,"difficultTerrain":false}},"1":{"0":{"inBounds":true,"difficultTerrain":false},"1":{"inBounds":true,"difficultTerrain":false},"2":{"inBounds":true,"difficultTerrain":false},"3":{"inBounds":true,"difficultTerrain":false},"4":{"inBounds":true,"difficultTerrain":false},"5":{"inBounds":true,"difficultTerrain":false},"6":{"inBounds":true,"difficultTerrain":false},"7":{"inBounds":true,"difficultTerrain":false},"8":{"inBounds":true,"difficultTerrain":false,"tileNumber":"06A"}},"2":{"0":{"inBounds":true,"difficultTerrain":false},"1":{"inBounds":true,"difficultTerrain":false},"2":{"inBounds":true,"difficultTerrain":false},"3":{"inBounds":true,"difficultTerrain":false},"4":{"inBounds":true,"difficultTerrain":false,"tileNumber":"16A"},"5":{"inBounds":true,"difficultTerrain":false},"6":{"inBounds":true,"difficultTerrain":true},"7":{"inBounds":true,"difficultTerrain":true},"8":{"inBounds":true,"difficultTerrain":false},"9":{"inBounds":true,"difficultTerrain":false,"tileNumber":"11A"},"10":{"inBounds":true,"difficultTerrain":false}},"3":{"0":{"inBounds":true,"difficultTerrain":false},"1":{"inBounds":true,"difficultTerrain":false},"2":{"inBounds":true,"difficultTerrain":false},"3":{"inBounds":true,"difficultTerrain":false},"5":{"inBounds":true,"difficultTerrain":false},"6":{"inBounds":true,"difficultTerrain":true},"7":{"inBounds":true,"difficultTerrain":true},"8":{"inBounds":true,"difficultTerrain":false},"9":{"inBounds":true,"difficultTerrain":false},"10":{"inBounds":true,"difficultTerrain":false}},"4":{"1":{"inBounds":true,"difficultTerrain":false},"2":{"inBounds":true,"difficultTerrain":false},"3":{"inBounds":true,"difficultTerrain":false},"5":{"inBounds":true,"difficultTerrain":false},"6":{"inBounds":true,"difficultTerrain":false},"7":{"inBounds":true,"difficultTerrain":false},"8":{"inBounds":true,"difficultTerrain":false},"9":{"inBounds":true,"difficultTerrain":false},"10":{"inBounds":true,"difficultTerrain":false},"11":{"inBounds":true,"difficultTerrain":false},"12":{"inBounds":true,"difficultTerrain":false}},"5":{"1":{"inBounds":true,"difficultTerrain":false},"2":{"inBounds":true,"difficultTerrain":false},"3":{"inBounds":true,"difficultTerrain":false},"4":{"inBounds":true,"difficultTerrain":false,"tileNumber":"36A"},"6":{"inBounds":true,"difficultTerrain":false,"tileNumber":"17A"},"7":{"inBounds":true,"difficultTerrain":false},"9":{"inBounds":true,"difficultTerrain":false},"10":{"inBounds":true,"difficultTerrain":false},"11":{"inBounds":true,"difficultTerrain":false},"12":{"inBounds":true,"difficultTerrain":false},"13":{"inBounds":true,"difficultTerrain":false,"tileNumber":"01A"}},"6":{"1":{"inBounds":true,"difficultTerrain":false},"2":{"inBounds":true,"difficultTerrain":false},"3":{"inBounds":true,"difficultTerrain":false,"tileNumber":"28A"},"4":{"inBounds":true,"difficultTerrain":false,"tileNumber":null},"5":{"inBounds":true,"difficultTerrain":false},"6":{"inBounds":true,"difficultTerrain":false},"7":{"inBounds":true,"difficultTerrain":false},"8":{"inBounds":true,"difficultTerrain":false},"9":{"inBounds":true,"difficultTerrain":false},"10":{"inBounds":true,"difficultTerrain":false},"11":{"inBounds":true,"difficultTerrain":false},"12":{"inBounds":true,"difficultTerrain":false},"13":{"inBounds":true,"difficultTerrain":false}},"7":{"4":{"inBounds":true,"difficultTerrain":false},"5":{"inBounds":true,"difficultTerrain":false},"6":{"inBounds":true,"difficultTerrain":false},"7":{"inBounds":true,"difficultTerrain":false},"8":{"inBounds":true,"difficultTerrain":false},"9":{"inBounds":true,"difficultTerrain":false},"10":{"inBounds":true,"difficultTerrain":false},"11":{"inBounds":true,"difficultTerrain":false},"12":{"inBounds":true,"difficultTerrain":true},"13":{"inBounds":true,"difficultTerrain":false},"14":{"inBounds":true,"difficultTerrain":false,"tileNumber":"18A"}},"8":{"4":{"inBounds":true,"difficultTerrain":false,"tileNumber":"18A"},"5":{"inBounds":true,"difficultTerrain":false},"6":{"inBounds":true,"difficultTerrain":false},"7":{"inBounds":true,"difficultTerrain":false},"8":{"inBounds":true,"difficultTerrain":false},"9":{"inBounds":true,"difficultTerrain":false},"10":{"inBounds":true,"difficultTerrain":false},"11":{"inBounds":true,"difficultTerrain":false},"12":{"inBounds":true,"difficultTerrain":true},"13":{"inBounds":true,"difficultTerrain":false},"14":{"inBounds":true,"difficultTerrain":false}},"9":{"5":{"inBounds":true,"difficultTerrain":false},"6":{"inBounds":true,"difficultTerrain":false},"7":{"inBounds":true,"difficultTerrain":false},"8":{"inBounds":true,"difficultTerrain":false,"tileNumber":"05A"},"9":{"inBounds":true,"difficultTerrain":false},"10":{"inBounds":true,"difficultTerrain":false},"11":{"inBounds":true,"difficultTerrain":false},"12":{"inBounds":true,"difficultTerrain":false},"13":{"inBounds":true,"difficultTerrain":false}},"10":{"4":{"inBounds":false,"difficultTerrain":false},"5":{"inBounds":false,"difficultTerrain":false},"6":{"inBounds":true,"difficultTerrain":false},"7":{"inBounds":true,"difficultTerrain":false,"tileNumber":"18A"},"9":{"inBounds":true,"difficultTerrain":false},"10":{"inBounds":true,"difficultTerrain":false},"11":{"inBounds":true,"difficultTerrain":false},"12":{"inBounds":true,"difficultTerrain":false},"13":{"inBounds":true,"difficultTerrain":false}},"11":{"9":{"inBounds":true,"difficultTerrain":false},"10":{"inBounds":true,"difficultTerrain":false},"11":{"inBounds":true,"difficultTerrain":false},"12":{"inBounds":true,"difficultTerrain":false}},"12":{"9":{"inBounds":true,"difficultTerrain":false},"10":{"inBounds":true,"difficultTerrain":false,"tileNumber":"18A"}}},"horizontal_edges":{"0":{"0":"Wall","1":"Wall","2":"Wall","3":"Wall"},"1":{"0":"CellBoundary","1":"CellBoundary","2":"Blocking","3":"CellBoundary","4":"Wall","5":"Wall","6":"Wall","7":"Wall","8":"Wall"},"2":{"0":"CellBoundary","1":"CellBoundary","2":"Blocking","3":"CellBoundary","4":"CellBoundary","5":"CellBoundary","6":"Difficult","7":"Difficult","8":"CellBoundary","9":"Wall","10":"Wall"},"3":{"0":"CellBoundary","1":"CellBoundary","2":"CellBoundary","3":"CellBoundary","4":"Wall","5":"CellBoundary","6":"Impassible","7":"Impassible","8":"CellBoundary","9":"CellBoundary","10":"CellBoundary"},"4":{"0":"Wall","1":"TileBoundary","2":"TileBoundary","3":"Wall","5":"Blocking","6":"Difficult","7":"Difficult","8":"Blocking","9":"TileBoundary","10":"TileBoundary","11":"Wall","12":"Wall"},"5":{"1":"CellBoundary","2":"CellBoundary","3":"CellBoundary","4":"Wall","5":"Wall","6":"TileBoundary","7":"TileBoundary","8":"Wall","9":"Blocking","10":"CellBoundary","11":"CellBoundary","12":"Blocking","13":"Wall"},"6":{"1":"CellBoundary","2":"CellBoundary","3":"CellBoundary","4":"CellBoundary","5":"Wall","6":"TileBoundary","7":"TileBoundary","8":"Wall","9":"Blocking","10":"Impassible","11":"Impassible","12":"CellBoundary","13":"Blocking"},"7":{"1":"Wall","2":"Wall","3":"Wall","4":"Wall","5":"CellBoundary","6":"Impassible","7":"Impassible","8":"CellBoundary","9":"CellBoundary","10":"CellBoundary","11":"CellBoundary","12":"Difficult","13":"CellBoundary","14":"Wall"},"8":{"4":"CellBoundary","5":"CellBoundary","6":"Blocking","7":"Blocking","8":"CellBoundary","9":"CellBoundary","10":"CellBoundary","11":"CellBoundary","12":"CellBoundary","13":"CellBoundary","14":"CellBoundary"},"9":{"4":"Wall","5":"CellBoundary","6":"Impassible","7":"Impassible","8":"CellBoundary","9":"CellBoundary","10":"CellBoundary","11":"CellBoundary","12":"Difficult","13":"CellBoundary","14":"Wall"},"10":{"5":"Wall","6":"TileBoundary","7":"TileBoundary","8":"Wall","9":"Blocking","10":"Impassible","11":"Impassible","12":"CellBoundary","13":"Blocking"},"11":{"6":"Wall","7":"Wall","9":"Blocking","10":"CellBoundary","11":"CellBoundary","12":"Blocking","13":"Wall"},"12":{"9":"TileBoundary","10":"TileBoundary","11":"Wall","12":"Wall"},"13":{"9":"Wall","10":"Wall"},"14":{},"15":{},"16":{},"17":{},"18":{},"19":{},"20":{},"21":{},"22":{},"23":{},"24":{},"25":{},"26":{},"27":{},"28":{},"29":{},"30":{},"31":{},"32":{},"33":{},"34":{},"35":{},"36":{},"37":{},"38":{},"39":{},"40":{},"41":{},"42":{},"43":{},"44":{},"45":{},"46":{},"47":{},"48":{},"49":{}},"vertical_edges":{"0":{"0":"Wall","1":"CellBoundary","2":"CellBoundary","3":"CellBoundary","4":"Wall"},"1":{"0":"Wall","1":"CellBoundary","2":"Blocking","3":"Blocking","4":"TileBoundary","5":"TileBoundary","6":"CellBoundary","7":"CellBoundary","8":"CellBoundary","9":"Wall"},"2":{"0":"Wall","1":"CellBoundary","2":"CellBoundary","3":"CellBoundary","4":"TileBoundary","5":"TileBoundary","6":"Difficult","7":"Impassible","8":"Difficult","9":"TileBoundary","10":"CellBoundary","11":"Wall"},"3":{"0":"Wall","1":"CellBoundary","2":"CellBoundary","3":"CellBoundary","4":"Wall","5":"Wall","6":"Difficult","7":"Impassible","8":"Difficult","9":"TileBoundary","10":"CellBoundary","11":"Wall"},"4":{"1":"Wall","2":"CellBoundary","3":"CellBoundary","4":"Wall","5":"Wall","6":"Blocking","7":"CellBoundary","8":"Blocking","9":"Wall","10":"CellBoundary","11":"CellBoundary","12":"Blocking","13":"Wall"},"5":{"1":"Wall","2":"CellBoundary","3":"CellBoundary","4":"TileBoundary","5":"Wall","6":"Wall","7":"CellBoundary","8":"Wall","9":"Wall","10":"Blocking","11":"CellBoundary","12":"CellBoundary","13":"Blocking","14":"Wall"},"6":{"1":"Wall","2":"CellBoundary","3":"CellBoundary","4":"TileBoundary","5":"Wall","6":"CellBoundary","7":"CellBoundary","8":"CellBoundary","9":"Wall","10":"CellBoundary","11":"CellBoundary","12":"CellBoundary","13":"CellBoundary","14":"Wall"},"7":{"4":"Wall","5":"TileBoundary","6":"Impassible","7":"Blocking","8":"Impassible","9":"TileBoundary","10":"CellBoundary","11":"CellBoundary","12":"Impassible","13":"Difficult","14":"TileBoundary","15":"Wall"},"8":{"4":"Wall","5":"TileBoundary","6":"Impassible","7":"Blocking","8":"Impassible","9":"TileBoundary","10":"CellBoundary","11":"CellBoundary","12":"Impassible","13":"Difficult","14":"TileBoundary","15":"Wall"},"9":{"5":"Wall","6":"CellBoundary","7":"CellBoundary","8":"CellBoundary","9":"Wall","10":"CellBoundary","11":"CellBoundary","12":"CellBoundary","13":"CellBoundary","14":"Wall"},"10":{"6":"Wall","7":"CellBoundary","8":"Wall","9":"Wall","10":"Blocking","11":"CellBoundary","12":"CellBoundary","13":"Blocking","14":"Wall"},"11":{"9":"Wall","10":"CellBoundary","11":"CellBoundary","12":"Blocking","13":"Wall"},"12":{"9":"Wall","10":"CellBoundary","11":"Wall"},"13":{},"14":{},"15":{},"16":{},"17":{},"18":{},"19":{},"20":{},"21":{},"22":{},"23":{},"24":{},"25":{},"26":{},"27":{},"28":{},"29":{},"30":{},"31":{},"32":{},"33":{},"34":{},"35":{},"36":{},"37":{},"38":{},"39":{},"40":{},"41":{},"42":{},"43":{},"44":{},"45":{},"46":{},"47":{},"48":{},"49":{}},"name":"Inside Man","briefingLocation":"Heart of the Empire Rulebook, page 20 (Wave 10)","mapType":"Story Mission","tileLists":[{"title":"Heart of the Empire","tiles":["01A","05A","06A","11A","16A","17A","18A","18A","18A","18A"]},{"title":"Core Game Map Tiles","tiles":["23A","28A","36A"]}]}
